duckduckgo_mcp_server/__init__.py
duckduckgo_mcp_server/server.py
mseep_duckduckgo_mcp_server-0.1.2.dist-info/licenses/LICENSE
mseep_duckduckgo_mcp_server-0.1.2.dist-info/METADATA
mseep_duckduckgo_mcp_server-0.1.2.dist-info/WHEEL
mseep_duckduckgo_mcp_server-0.1.2.dist-info/entry_points.txt
mseep_duckduckgo_mcp_server-0.1.2.dist-info/top_level.txt
mseep_duckduckgo_mcp_server-0.1.2.dist-info/RECORD
