Metadata-Version: 2.4
Name: mseep-duckduckgo-mcp-server
Version: 0.1.2
Summary: MCP Server for searching via DuckDuckGo
Author-email: mseep <support@skydeck.ai>
Project-URL: Homepage, https://github.com/nickclyde/duckduckgo-mcp-server
Project-URL: Issues, https://github.com/nickclyde/duckduckgo-mcp-server/issues
Classifier: Development Status :: 3 - Alpha
Classifier: Intended Audience :: Developers
Classifier: License :: OSI Approved :: MIT License
Classifier: Programming Language :: Python :: 3
Classifier: Programming Language :: Python :: 3.10
Classifier: Programming Language :: Python :: 3.11
Classifier: Programming Language :: Python :: 3.12
Classifier: Programming Language :: Python :: 3.13
Requires-Python: >=3.10
License-File: LICENSE
Requires-Dist: beautifulsoup4>=4.13.3
Requires-Dist: httpx>=0.28.1
Requires-Dist: mcp[cli]>=1.3.0
Dynamic: license-file
